LICENSE
MANIFEST.in
README.rst
setup.cfg
setup.py
mistune_hilite/__init__.py
mistune_hilite.egg-info/PKG-INFO
mistune_hilite.egg-info/SOURCES.txt
mistune_hilite.egg-info/dependency_links.txt
mistune_hilite.egg-info/requires.txt
mistune_hilite.egg-info/top_level.txt