Metadata-Version: 1.1
Name: mistune-hilite
Version: 0.1.0
Summary: Python-Markdown Code Hilite port for Mistune
Home-page: https://github.com/dvl/mistune-hilite
Author: André Luiz
Author-email: contato@xdvl.info
License: MIT
Keywords: sintax highlight hilite mistune
Platform: UNKNOWN
Classifier: Development Status :: 4 - Beta
Classifier: Environment :: Web Environment
Classifier: Intended Audience :: Developers
Classifier: License :: OSI Approved :: MIT License
Classifier: Operating System :: OS Independent
Classifier: Programming Language :: Python
Classifier: Programming Language :: Python :: 2
Classifier: Programming Language :: Python :: 3
Classifier: Topic :: Software Development :: Libraries :: Python Modules
Classifier: Topic :: Text Processing :: Filters
Classifier: Topic :: Text Processing :: Markup
Classifier: Topic :: Utilities
